odoo/addons/account_payment_term_restriction_purchase/README.rst
odoo/addons/account_payment_term_restriction_purchase/__init__.py
odoo/addons/account_payment_term_restriction_purchase/__manifest__.py
odoo/addons/account_payment_term_restriction_purchase/i18n/account_payment_term_restriction_purchase.pot
odoo/addons/account_payment_term_restriction_purchase/models/__init__.py
odoo/addons/account_payment_term_restriction_purchase/models/purchase_order.py
odoo/addons/account_payment_term_restriction_purchase/models/res_partner.py
odoo/addons/account_payment_term_restriction_purchase/readme/CONTRIBUTORS.rst
odoo/addons/account_payment_term_restriction_purchase/readme/DESCRIPTION.rst
odoo/addons/account_payment_term_restriction_purchase/static/description/icon.png
odoo/addons/account_payment_term_restriction_purchase/static/description/index.html
odoo/addons/account_payment_term_restriction_purchase/tests/__init__.py
odoo/addons/account_payment_term_restriction_purchase/tests/test_account_payment_term_restriction_purchase.py
odoo13_addon_account_payment_term_restriction_purchase-13.0.1.0.1.dev5.dist-info/METADATA
odoo13_addon_account_payment_term_restriction_purchase-13.0.1.0.1.dev5.dist-info/WHEEL
odoo13_addon_account_payment_term_restriction_purchase-13.0.1.0.1.dev5.dist-info/top_level.txt
odoo13_addon_account_payment_term_restriction_purchase-13.0.1.0.1.dev5.dist-info/RECORD
